runpod_llm/__init__.py
runpod_llm/core.py
runpod_llm/llama2.py
runpod_llm/models.py
runpod_llm/version.py
langchain_runpod_llm-0.0.5.dist-info/LICENSE
langchain_runpod_llm-0.0.5.dist-info/METADATA
langchain_runpod_llm-0.0.5.dist-info/WHEEL
langchain_runpod_llm-0.0.5.dist-info/top_level.txt
langchain_runpod_llm-0.0.5.dist-info/RECORD
